moudle/__init__.py
moudle/utils_luTuo.py
utilsLuTuo-1.0.dist-info/LICENSE
utilsLuTuo-1.0.dist-info/METADATA
utilsLuTuo-1.0.dist-info/WHEEL
utilsLuTuo-1.0.dist-info/top_level.txt
utilsLuTuo-1.0.dist-info/RECORD
