Metadata-Version: 2.1
Name: utilsLuTuo
Version: 1.0
Summary: luTuoTest
Author: LuTuo
Author-email: 1803228677@qq.com
Requires-Python: >=3.6
License-File: LICENSE
